[
    {
        "日期":"2024-06-16",
        "最新价":1555.0,
        "市盈率估值买点":1110,
        "净利润估值买点":1254
    },
    {
        "日期":"2024-06-17",
        "最新价":1541.5,
        "市盈率估值买点":1117,
        "净利润估值买点":1263
    },
    {
        "日期":"2024-06-18",
        "最新价":1531.91,
        "市盈率估值买点":1110,
        "净利润估值买点":1255
    },
    {
        "日期":"2024-06-19",
        "最新价":1496.1,
        "市盈率估值买点":1116,
        "净利润估值买点":1246
    },
    {
        "日期":"2024-06-21",
        "最新价":1475.1,
        "市盈率估值买点":1117,
        "净利润估值买点":1250
    },
    {
        "日期":"2024-06-24",
        "最新价":1476.55,
        "市盈率估值买点":1118,
        "净利润估值买点":1251
    },
    {
        "日期":"2024-06-25",
        "最新价":1486.65,
        "市盈率估值买点":1109,
        "净利润估值买点":1259
    },
    {
        "日期":"2024-06-26",
        "最新价":1489.22,
        "市盈率估值买点":1111,
        "净利润估值买点":1262
    },
    {
        "日期":"2024-06-28",
        "最新价":1467.39,
        "市盈率估值买点":1111,
        "净利润估值买点":1243
    },
    {
        "日期":"2024-07-01",
        "最新价":1440.38,
        "市盈率估值买点":1107,
        "净利润估值买点":1263
    },
    {
        "日期":"2024-07-03",
        "最新价":1500.0,
        "市盈率估值买点":1119,
        "净利润估值买点":1250
    },
    {
        "日期":"2024-07-05",
        "最新价":1453.0,
        "市盈率估值买点":1117,
        "净利润估值买点":1252
    },
    {
        "日期":"2024-07-08",
        "最新价":1420.0,
        "市盈率估值买点":1109,
        "净利润估值买点":1245
    },
    {
        "日期":"2024-07-10",
        "最新价":1437.59,
        "市盈率估值买点":1105,
        "净利润估值买点":1261
    },
    {
        "日期":"2024-07-12",
        "最新价":1478.82,
        "市盈率估值买点":1103,
        "净利润估值买点":1253
    },
    {
        "日期":"2024-07-15",
        "最新价":1474.9,
        "市盈率估值买点":1100,
        "净利润估值买点":1249
    },
    {
        "日期":"2024-07-17",
        "最新价":1501.4,
        "市盈率估值买点":1103,
        "净利润估值买点":1251
    },
    {
        "日期":"2024-07-18",
        "最新价":1497.51,
        "市盈率估值买点":1101,
        "净利润估值买点":1247
    },
    {
        "日期":"2024-07-19",
        "最新价":1525.62,
        "市盈率估值买点":1105,
        "净利润估值买点":1250
    },
    {
        "日期":"2024-07-20",
        "最新价":1525.62,
        "市盈率估值买点":1105,
        "净利润估值买点":1250
    },
    {
        "日期":"2024-07-22",
        "最新价":1499.0,
        "市盈率估值买点":1102,
        "净利润估值买点":1249
    },
    {
        "日期":"2024-07-23",
        "最新价":1455.0,
        "市盈率估值买点":1102,
        "净利润估值买点":1254
    },
    {
        "日期":"2024-07-24",
        "最新价":1440.02,
        "市盈率估值买点":1107,
        "净利润估值买点":1241
    },
    {
        "日期":"2024-07-25",
        "最新价":1430.49,
        "市盈率估值买点":1100,
        "净利润估值买点":1254
    },
    {
        "日期":"2024-07-26",
        "最新价":1422.19,
        "市盈率估值买点":1111,
        "净利润估值买点":1247
    },
    {
        "日期":"2024-07-29",
        "最新价":1398.02,
        "市盈率估值买点":1109,
        "净利润估值买点":1248
    },
    {
        "日期":"2024-07-30",
        "最新价":1379.99,
        "市盈率估值买点":1112,
        "净利润估值买点":1254
    },
    {
        "日期":"2024-07-31",
        "最新价":1421.28,
        "市盈率估值买点":1110,
        "净利润估值买点":1246
    },
    {
        "日期":"2024-08-01",
        "最新价":1386.16,
        "市盈率估值买点":1100,
        "净利润估值买点":1237
    },
    {
        "日期":"2024-08-02",
        "最新价":1385.45,
        "市盈率估值买点":1099,
        "净利润估值买点":1237
    },
    {
        "日期":"2024-08-05",
        "最新价":1410.01,
        "市盈率估值买点":1101,
        "净利润估值买点":1236
    },
    {
        "日期":"2024-08-06",
        "最新价":1404.7,
        "市盈率估值买点":1097,
        "净利润估值买点":1232
    },
    {
        "日期":"2024-08-07",
        "最新价":1415.5,
        "市盈率估值买点":1105,
        "净利润估值买点":1241
    },
    {
        "日期":"2024-08-08",
        "最新价":1430.69,
        "市盈率估值买点":1100,
        "净利润估值买点":1233
    },
    {
        "日期":"2024-08-09",
        "最新价":1436.8,
        "市盈率估值买点":1140,
        "净利润估值买点":1238
    },
    {
        "日期":"2024-08-12",
        "最新价":1436.1,
        "市盈率估值买点":1139,
        "净利润估值买点":1238
    },
    {
        "日期":"2024-08-13",
        "最新价":1423.01,
        "市盈率估值买点":1129,
        "净利润估值买点":1248
    },
    {
        "日期":"2024-08-14",
        "最新价":1413.3,
        "市盈率估值买点":1139,
        "净利润估值买点":1239
    },
    {
        "日期":"2024-08-15",
        "最新价":1426.89,
        "市盈率估值买点":1132,
        "净利润估值买点":1230
    },
    {
        "日期":"2024-08-16",
        "最新价":1431.2,
        "市盈率估值买点":1135,
        "净利润估值买点":1212
    },
    {
        "日期":"2024-08-19",
        "最新价":1425.44,
        "市盈率估值买点":1131,
        "净利润估值买点":1228
    },
    {
        "日期":"2024-08-20",
        "最新价":1422.72,
        "市盈率估值买点":1129,
        "净利润估值买点":1226
    },
    {
        "日期":"2024-08-21",
        "最新价":1417.58,
        "市盈率估值买点":1125,
        "净利润估值买点":1181
    },
    {
        "日期":"2024-08-22",
        "最新价":1410.05,
        "市盈率估值买点":1137,
        "净利润估值买点":1175
    },
    {
        "日期":"2024-08-23",
        "最新价":1414.99,
        "市盈率估值买点":1123,
        "净利润估值买点":1179
    },
    {
        "日期":"2024-08-26",
        "最新价":1412.0,
        "市盈率估值买点":1138,
        "净利润估值买点":1176
    },
    {
        "日期":"2024-08-27",
        "最新价":1404.07,
        "市盈率估值买点":1132,
        "净利润估值买点":1170
    },
    {
        "日期":"2024-08-28",
        "最新价":1389.0,
        "市盈率估值买点":1138,
        "净利润估值买点":1177
    },
    {
        "日期":"2024-08-29",
        "最新价":1413.3,
        "市盈率估值买点":1139,
        "净利润估值买点":1177
    },
    {
        "日期":"2024-08-30",
        "最新价":1443.19,
        "市盈率估值买点":1127,
        "净利润估值买点":1163
    },
    {
        "日期":"2024-09-02",
        "最新价":1395.0,
        "市盈率估值买点":1125,
        "净利润估值买点":1162
    },
    {
        "日期":"2024-09-03",
        "最新价":1410.0,
        "市盈率估值买点":1137,
        "净利润估值买点":1175
    },
    {
        "日期":"2024-09-05",
        "最新价":1404.88,
        "市盈率估值买点":1132,
        "净利润估值买点":1170
    },
    {
        "日期":"2024-09-06",
        "最新价":1398.0,
        "市盈率估值买点":1127,
        "净利润估值买点":1165
    },
    {
        "日期":"2024-09-09",
        "最新价":1375.0,
        "市盈率估值买点":1127,
        "净利润估值买点":1165
    },
    {
        "日期":"2024-09-10",
        "最新价":1378.0,
        "市盈率估值买点":1129,
        "净利润估值买点":1167
    },
    {
        "日期":"2024-09-11",
        "最新价":1380.0,
        "市盈率估值买点":1131,
        "净利润估值买点":1169
    },
    {
        "日期":"2024-09-12",
        "最新价":1335.06,
        "市盈率估值买点":1131,
        "净利润估值买点":1171
    },
    {
        "日期":"2024-09-13",
        "最新价":1304.13,
        "市盈率估值买点":1124,
        "净利润估值买点":1164
    },
    {
        "日期":"2024-09-16",
        "最新价":1304.13,
        "市盈率估值买点":1124,
        "净利润估值买点":1164
    },
    {
        "日期":"2024-09-17",
        "最新价":1304.13,
        "市盈率估值买点":1124,
        "净利润估值买点":1164
    },
    {
        "日期":"2024-09-19",
        "最新价":1261.0,
        "市盈率估值买点":1125,
        "净利润估值买点":1212
    },
    {
        "日期":"2024-09-20",
        "最新价":1263.92,
        "市盈率估值买点":1128,
        "净利润估值买点":1215
    },
    {
        "日期":"2024-09-23",
        "最新价":1261.54,
        "市盈率估值买点":1126,
        "净利润估值买点":1213
    },
    {
        "日期":"2024-09-24",
        "最新价":1372.6,
        "市盈率估值买点":1125,
        "净利润估值买点":1204
    },
    {
        "日期":"2024-09-25",
        "最新价":1399.0,
        "市盈率估值买点":1128,
        "净利润估值买点":1206
    },
    {
        "日期":"2024-09-26",
        "最新价":1529.0,
        "市盈率估值买点":1124,
        "净利润估值买点":1213
    },
    {
        "日期":"2024-09-27",
        "最新价":1629.2,
        "市盈率估值买点":1115,
        "净利润估值买点":1197
    },
    {
        "日期":"2024-09-30",
        "最新价":1748.0,
        "市盈率估值买点":1120,
        "净利润估值买点":1213
    },
    {
        "日期":"2024-10-01",
        "最新价":1748.0,
        "市盈率估值买点":1120,
        "净利润估值买点":1213
    },
    {
        "日期":"2024-10-02",
        "最新价":1748.0,
        "市盈率估值买点":1120,
        "净利润估值买点":1213
    },
    {
        "日期":"2024-10-07",
        "最新价":1748.0,
        "市盈率估值买点":1120,
        "净利润估值买点":1213
    },
    {
        "日期":"2024-10-08",
        "最新价":1723.0,
        "市盈率估值买点":1118,
        "净利润估值买点":1213
    },
    {
        "日期":"2024-10-09",
        "最新价":1595.15,
        "市盈率估值买点":1123,
        "净利润估值买点":1208
    },
    {
        "日期":"2024-10-10",
        "最新价":1640.0,
        "市盈率估值买点":1123,
        "净利润估值买点":1205
    },
    {
        "日期":"2024-10-11",
        "最新价":1604.99,
        "市盈率估值买点":1114,
        "净利润估值买点":1197
    },
    {
        "日期":"2024-10-14",
        "最新价":1601.99,
        "市盈率估值买点":1112,
        "净利润估值买点":1195
    },
    {
        "日期":"2024-10-15",
        "最新价":1554.25,
        "市盈率估值买点":1110,
        "净利润估值买点":1195
    },
    {
        "日期":"2024-10-16",
        "最新价":1522.5,
        "市盈率估值买点":1119,
        "净利润估值买点":1208
    },
    {
        "日期":"2024-10-17",
        "最新价":1494.6,
        "市盈率估值买点":1115,
        "净利润估值买点":1205
    },
    {
        "日期":"2024-10-22",
        "最新价":1543.0,
        "市盈率估值买点":1118,
        "净利润估值买点":1205
    },
    {
        "日期":"2024-10-23",
        "最新价":1567.5,
        "市盈率估值买点":1119,
        "净利润估值买点":1205
    },
    {
        "日期":"2024-10-24",
        "最新价":1552.2,
        "市盈率估值买点":1108,
        "净利润估值买点":1194
    },
    {
        "日期":"2024-10-25",
        "最新价":1558.85,
        "市盈率估值买点":1113,
        "净利润估值买点":1199
    },
    {
        "日期":"2024-10-28",
        "最新价":1565.0,
        "市盈率估值买点":1134,
        "净利润估值买点":1203
    },
    {
        "日期":"2024-10-29",
        "最新价":1531.62,
        "市盈率估值买点":1142,
        "净利润估值买点":1196
    },
    {
        "日期":"2024-10-30",
        "最新价":1532.0,
        "市盈率估值买点":1143,
        "净利润估值买点":1196
    },
    {
        "日期":"2024-10-31",
        "最新价":1527.79,
        "市盈率估值买点":1140,
        "净利润估值买点":1193
    },
    {
        "日期":"2024-11-01",
        "最新价":1533.75,
        "市盈率估值买点":1144,
        "净利润估值买点":1161
    },
    {
        "日期":"2024-11-04",
        "最新价":1548.2,
        "市盈率估值买点":1138,
        "净利润估值买点":1155
    },
    {
        "日期":"2024-11-05",
        "最新价":1576.99,
        "市盈率估值买点":1142,
        "净利润估值买点":1159
    },
    {
        "日期":"2024-11-06",
        "最新价":1571.0,
        "市盈率估值买点":1138,
        "净利润估值买点":1155
    },
    {
        "日期":"2024-11-07",
        "最新价":1649.14,
        "市盈率估值买点":1145,
        "净利润估值买点":1161
    },
    {
        "日期":"2024-11-08",
        "最新价":1609.97,
        "市盈率估值买点":1133,
        "净利润估值买点":1149
    },
    {
        "日期":"2024-11-11",
        "最新价":1598.01,
        "市盈率估值买点":1141,
        "净利润估值买点":1157
    },
    {
        "日期":"2024-11-12",
        "最新价":1577.2,
        "市盈率估值买点":1142,
        "净利润估值买点":1159
    },
    {
        "日期":"2024-11-13",
        "最新价":1578.5,
        "市盈率估值买点":1143,
        "净利润估值买点":1143
    },
    {
        "日期":"2024-11-14",
        "最新价":1573.8,
        "市盈率估值买点":1140,
        "净利润估值买点":1157
    },
    {
        "日期":"2024-11-15",
        "最新价":1559.0,
        "市盈率估值买点":1129,
        "净利润估值买点":1146
    },
    {
        "日期":"2024-12-16",
        "最新价":1527.2,
        "市盈率估值买点":1139,
        "净利润估值买点":1139
    },
    {
        "日期":"2024-12-19",
        "最新价":1551.01,
        "市盈率估值买点":1140,
        "净利润估值买点":1140
    },
    {
        "日期":"2024-12-20",
        "最新价":1522.0,
        "市盈率估值买点":1119,
        "净利润估值买点":1119
    },
    {
        "日期":"2024-12-23",
        "最新价":1526.45,
        "市盈率估值买点":1122,
        "净利润估值买点":1122
    },
    {
        "日期":"2024-12-24",
        "最新价":1538.82,
        "市盈率估值买点":1115,
        "净利润估值买点":1131
    },
    {
        "日期":"2024-12-25",
        "最新价":1530.0,
        "市盈率估值买点":1125,
        "净利润估值买点":1125
    },
    {
        "日期":"2024-12-26",
        "最新价":1527.79,
        "市盈率估值买点":1123,
        "净利润估值买点":1123
    },
    {
        "日期":"2024-12-27",
        "最新价":1528.97,
        "市盈率估值买点":1124,
        "净利润估值买点":1124
    },
    {
        "日期":"2024-12-30",
        "最新价":1525.0,
        "市盈率估值买点":1121,
        "净利润估值买点":1121
    },
    {
        "日期":"2024-12-31",
        "最新价":1524.0,
        "市盈率估值买点":1120,
        "净利润估值买点":1120
    },
    {
        "日期":"2025-01-01",
        "最新价":1524.0,
        "市盈率估值买点":1120,
        "净利润估值买点":1120
    },
    {
        "日期":"2025-01-02",
        "最新价":1488.0,
        "市盈率估值买点":1110,
        "净利润估值买点":1127
    },
    {
        "日期":"2025-01-03",
        "最新价":1475.0,
        "市盈率估值买点":1117,
        "净利润估值买点":1100
    },
    {
        "日期":"2025-01-16",
        "最新价":1446.38,
        "市盈率估值买点":1112,
        "净利润估值买点":1112
    },
    {
        "日期":"2025-01-17",
        "最新价":1454.75,
        "市盈率估值买点":1119,
        "净利润估值买点":1102
    },
    {
        "日期":"2025-01-20",
        "最新价":1474.8,
        "市盈率估值买点":1117,
        "净利润估值买点":1100
    },
    {
        "日期":"2025-01-21",
        "最新价":1468.15,
        "市盈率估值买点":1112,
        "净利润估值买点":1095
    },
    {
        "日期":"2025-01-22",
        "最新价":1441.0,
        "市盈率估值买点":1108,
        "净利润估值买点":1091
    },
    {
        "日期":"2025-01-23",
        "最新价":1443.0,
        "市盈率估值买点":1110,
        "净利润估值买点":1093
    },
    {
        "日期":"2025-01-24",
        "最新价":1436.0,
        "市盈率估值买点":1104,
        "净利润估值买点":1087
    },
    {
        "日期":"2025-01-27",
        "最新价":1434.99,
        "市盈率估值买点":1103,
        "净利润估值买点":1087
    },
    {
        "日期":"2025-01-28",
        "最新价":1434.99,
        "市盈率估值买点":1103,
        "净利润估值买点":1087
    },
    {
        "日期":"2025-01-29",
        "最新价":1434.99,
        "市盈率估值买点":1103,
        "净利润估值买点":1087
    },
    {
        "日期":"2025-01-30",
        "最新价":1434.99,
        "市盈率估值买点":1103,
        "净利润估值买点":1087
    },
    {
        "日期":"2025-01-31",
        "最新价":1434.99,
        "市盈率估值买点":1103,
        "净利润估值买点":1087
    },
    {
        "日期":"2025-02-01",
        "最新价":1434.99,
        "市盈率估值买点":1103,
        "净利润估值买点":1087
    }
]