[
    {
        "日期":"2025-05-27",
        "股票代码":"600519",
        "股票名称":"贵州茅台",
        "市盈率估值":0.67,
        "净利润估值":0.69,
        "最新价":1543.9,
        "市盈率估值买点":1152,
        "净利润估值买点":1118,
        "PE_90分位":48.65929,
        "市盈率(TTM)":21.789,
        "合理市盈率":32.625,
        "股息率(TTM)":3.547,
        "预测净利润(3Y)":1077.58
    },
    {
        "日期":"2025-05-27",
        "股票代码":"hk00700",
        "股票名称":"腾讯控股",
        "市盈率估值":1.27,
        "净利润估值":1.28,
        "最新价":512.0,
        "市盈率估值买点":241,
        "净利润估值买点":240,
        "PE_90分位":50.138,
        "市盈率(TTM)":22.1603,
        "合理市盈率":17.46,
        "股息率(TTM)":0.88,
        "预测净利润(3Y)":2628.065
    },
    {
        "日期":"2025-05-27",
        "股票代码":"hk09633",
        "股票名称":"农夫山泉",
        "市盈率估值":0.75,
        "净利润估值":0.72,
        "最新价":38.05,
        "市盈率估值买点":25,
        "净利润估值买点":26,
        "PE_90分位":78.036,
        "市盈率(TTM)":33.1904,
        "合理市盈率":43.97,
        "股息率(TTM)":2.18,
        "预测净利润(3Y)":168.9655
    },
    {
        "日期":"2025-05-27",
        "股票代码":"hk00388",
        "股票名称":"港交所",
        "市盈率估值":1.04,
        "净利润估值":1.23,
        "最新价":398.2,
        "市盈率估值买点":191,
        "净利润估值买点":161,
        "PE_90分位":49.05,
        "市盈率(TTM)":35.661,
        "合理市盈率":34.34,
        "股息率(TTM)":2.33,
        "预测净利润(3Y)":149.87
    },
    {
        "日期":"2025-05-27",
        "股票代码":"000858",
        "股票名称":"五粮液",
        "市盈率估值":0.64,
        "净利润估值":0.71,
        "最新价":126.16,
        "市盈率估值买点":98,
        "净利润估值买点":88,
        "PE_90分位":44.56446,
        "市盈率(TTM)":14.99,
        "合理市盈率":23.56,
        "股息率(TTM)":5.744,
        "预测净利润(3Y)":368.05
    },
    {
        "日期":"2025-05-27",
        "股票代码":"000568",
        "股票名称":"泸州老窖",
        "市盈率估值":0.5,
        "净利润估值":0.55,
        "最新价":119.18,
        "市盈率估值买点":119,
        "净利润估值买点":108,
        "PE_90分位":45.43086,
        "市盈率(TTM)":13.002,
        "合理市盈率":25.77,
        "股息率(TTM)":5.67,
        "预测净利润(3Y)":153.67
    },
    {
        "日期":"2025-05-27",
        "股票代码":"002304",
        "股票名称":"洋河股份",
        "市盈率估值":1.15,
        "净利润估值":1.16,
        "最新价":66.38,
        "市盈率估值买点":28,
        "净利润估值买点":28,
        "PE_90分位":34.0281,
        "市盈率(TTM)":23.5,
        "合理市盈率":20.415,
        "股息率(TTM)":10.53,
        "预测净利润(3Y)":52.88
    },
    {
        "日期":"2025-05-27",
        "股票代码":"600600",
        "股票名称":"青岛啤酒",
        "市盈率估值":0.72,
        "净利润估值":0.74,
        "最新价":73.75,
        "市盈率估值买点":51,
        "净利润估值买点":49,
        "PE_90分位":51.3317,
        "市盈率(TTM)":22.568,
        "合理市盈率":31.425,
        "股息率(TTM)":2.712,
        "预测净利润(3Y)":54.03
    },
    {
        "日期":"2025-05-27",
        "股票代码":"605499",
        "股票名称":"东鹏饮料",
        "市盈率估值":1.0,
        "净利润估值":0.72,
        "最新价":293.0,
        "市盈率估值买点":146,
        "净利润估值买点":203,
        "PE_90分位":68.1396,
        "市盈率(TTM)":41.826,
        "合理市盈率":41.845,
        "股息率(TTM)":1.51,
        "预测净利润(3Y)":63.62
    },
    {
        "日期":"2025-05-27",
        "股票代码":"000848",
        "股票名称":"承德露露",
        "市盈率估值":1.2,
        "净利润估值":1.15,
        "最新价":11.05,
        "市盈率估值买点":5,
        "净利润估值买点":5,
        "PE_90分位":24.62404,
        "市盈率(TTM)":18.306,
        "合理市盈率":15.26,
        "股息率(TTM)":3.62,
        "预测净利润(3Y)":8.29
    },
    {
        "日期":"2025-05-27",
        "股票代码":"600436",
        "股票名称":"片仔癀",
        "市盈率估值":0.68,
        "净利润估值":0.67,
        "最新价":204.07,
        "市盈率估值买点":150,
        "净利润估值买点":152,
        "PE_90分位":101.22489,
        "市盈率(TTM)":41.008,
        "合理市盈率":60.335,
        "股息率(TTM)":1.7,
        "预测净利润(3Y)":38.27
    },
    {
        "日期":"2025-05-27",
        "股票代码":"000538",
        "股票名称":"云南白药",
        "市盈率估值":0.81,
        "净利润估值":0.83,
        "最新价":56.16,
        "市盈率估值买点":34,
        "净利润估值买点":33,
        "PE_90分位":35.24788,
        "市盈率(TTM)":20.113,
        "合理市盈率":24.98,
        "股息率(TTM)":2.11,
        "预测净利润(3Y)":60.59
    },
    {
        "日期":"2025-05-27",
        "股票代码":"600329",
        "股票名称":"达仁堂",
        "市盈率估值":0.5,
        "净利润估值":1.31,
        "最新价":33.05,
        "市盈率估值买点":33,
        "净利润估值买点":12,
        "PE_90分位":32.7103,
        "市盈率(TTM)":11.484,
        "合理市盈率":22.795,
        "股息率(TTM)":3.873,
        "预测净利润(3Y)":10.68
    },
    {
        "日期":"2025-05-27",
        "股票代码":"000999",
        "股票名称":"华润三九",
        "市盈率估值":1.0,
        "净利润估值":0.84,
        "最新价":42.04,
        "市盈率估值买点":25,
        "净利润估值买点":30,
        "PE_90分位":22.83085,
        "市盈率(TTM)":16.49,
        "合理市盈率":16.415,
        "股息率(TTM)":5.124,
        "预测净利润(3Y)":48.75
    },
    {
        "日期":"2025-05-27",
        "股票代码":"600276",
        "股票名称":"恒瑞医药",
        "市盈率估值":0.89,
        "净利润估值":0.85,
        "最新价":53.42,
        "市盈率估值买点":30,
        "净利润估值买点":31,
        "PE_90分位":81.6667,
        "市盈率(TTM)":51.561,
        "合理市盈率":57.875,
        "股息率(TTM)":0.361,
        "预测净利润(3Y)":89.71
    },
    {
        "日期":"2025-05-27",
        "股票代码":"603259",
        "股票名称":"药明康德",
        "市盈率估值":0.47,
        "净利润估值":0.46,
        "最新价":62.2,
        "市盈率估值买点":66,
        "净利润估值买点":67,
        "PE_90分位":108.26182,
        "市盈率(TTM)":16.067,
        "合理市盈率":34.215,
        "股息率(TTM)":1.579,
        "预测净利润(3Y)":141.59
    },
    {
        "日期":"2025-05-27",
        "股票代码":"300760",
        "股票名称":"迈瑞医疗",
        "市盈率估值":0.67,
        "净利润估值":0.6,
        "最新价":227.28,
        "市盈率估值买点":169,
        "净利润估值买点":189,
        "PE_90分位":76.1374,
        "市盈率(TTM)":24.743,
        "合理市盈率":36.755,
        "股息率(TTM)":3.172,
        "预测净利润(3Y)":157.18
    },
    {
        "日期":"2025-05-27",
        "股票代码":"002262",
        "股票名称":"恩华药业",
        "市盈率估值":0.96,
        "净利润估值":0.84,
        "最新价":22.43,
        "市盈率估值买点":11,
        "净利润估值买点":13,
        "PE_90分位":45.87789,
        "市盈率(TTM)":19.333,
        "合理市盈率":20.24,
        "股息率(TTM)":1.605,
        "预测净利润(3Y)":16.79
    },
    {
        "日期":"2025-05-27",
        "股票代码":"603288",
        "股票名称":"海天味业",
        "市盈率估值":0.8,
        "净利润估值":0.81,
        "最新价":44.52,
        "市盈率估值买点":27,
        "净利润估值买点":27,
        "PE_90分位":77.30735,
        "市盈率(TTM)":37.353,
        "合理市盈率":46.87,
        "股息率(TTM)":1.482,
        "预测净利润(3Y)":81.56
    },
    {
        "日期":"2025-05-27",
        "股票代码":"600887",
        "股票名称":"伊利股份",
        "市盈率估值":1.35,
        "净利润估值":1.0,
        "最新价":30.63,
        "市盈率估值买点":13,
        "净利润估值买点":18,
        "PE_90分位":31.65858,
        "市盈率(TTM)":26.167,
        "合理市盈率":19.435,
        "股息率(TTM)":3.944,
        "预测净利润(3Y)":124.15
    },
    {
        "日期":"2025-05-27",
        "股票代码":"000895",
        "股票名称":"双汇发展",
        "市盈率估值":0.99,
        "净利润估值":1.09,
        "最新价":24.28,
        "市盈率估值买点":14,
        "净利润估值买点":13,
        "PE_90分位":23.13852,
        "市盈率(TTM)":17.328,
        "合理市盈率":17.445,
        "股息率(TTM)":5.807,
        "预测净利润(3Y)":55.15
    },
    {
        "日期":"2025-05-27",
        "股票代码":"002032",
        "股票名称":"苏泊尔",
        "市盈率估值":0.96,
        "净利润估值":1.04,
        "最新价":54.8,
        "市盈率估值买点":28,
        "净利润估值买点":26,
        "PE_90分位":33.72934,
        "市盈率(TTM)":19.331,
        "合理市盈率":20.155,
        "股息率(TTM)":5.128,
        "预测净利润(3Y)":26.09
    },
    {
        "日期":"2025-05-27",
        "股票代码":"600690",
        "股票名称":"海尔智家",
        "市盈率估值":0.8,
        "净利润估值":0.8,
        "最新价":25.22,
        "市盈率估值买点":18,
        "净利润估值买点":18,
        "PE_90分位":22.54435,
        "市盈率(TTM)":12.16,
        "合理市盈率":15.175,
        "股息率(TTM)":3.196,
        "预测净利润(3Y)":244.28
    },
    {
        "日期":"2025-05-27",
        "股票代码":"000333",
        "股票名称":"美的集团",
        "市盈率估值":1.05,
        "净利润估值":1.12,
        "最新价":78.48,
        "市盈率估值买点":44,
        "净利润估值买点":42,
        "PE_90分位":21.27985,
        "市盈率(TTM)":14.354,
        "合理市盈率":13.64,
        "股息率(TTM)":3.475,
        "预测净利润(3Y)":493.45
    },
    {
        "日期":"2025-05-27",
        "股票代码":"603195",
        "股票名称":"公牛集团",
        "市盈率估值":0.78,
        "净利润估值":0.8,
        "最新价":71.35,
        "市盈率估值买点":45,
        "净利润估值买点":44,
        "PE_90分位":49.57366,
        "市盈率(TTM)":21.352,
        "合理市盈率":27.375,
        "股息率(TTM)":2.998,
        "预测净利润(3Y)":52.54
    },
    {
        "日期":"2025-05-27",
        "股票代码":"600660",
        "股票名称":"福耀玻璃",
        "市盈率估值":0.82,
        "净利润估值":0.71,
        "最新价":58.6,
        "市盈率估值买点":35,
        "净利润估值买点":41,
        "PE_90分位":36.27723,
        "市盈率(TTM)":18.788,
        "合理市盈率":22.905,
        "股息率(TTM)":3.072,
        "预测净利润(3Y)":116.9
    },
    {
        "日期":"2025-05-27",
        "股票代码":"002415",
        "股票名称":"海康威视",
        "市盈率估值":0.94,
        "净利润估值":0.84,
        "最新价":28.11,
        "市盈率估值买点":14,
        "净利润估值买点":16,
        "PE_90分位":39.28352,
        "市盈率(TTM)":21.45,
        "合理市盈率":22.79,
        "股息率(TTM)":2.49,
        "预测净利润(3Y)":170.13
    },
    {
        "日期":"2025-05-27",
        "股票代码":"603899",
        "股票名称":"晨光股份",
        "市盈率估值":0.71,
        "净利润估值":0.63,
        "最新价":28.7,
        "市盈率估值买点":20,
        "净利润估值买点":22,
        "PE_90分位":56.56834,
        "市盈率(TTM)":19.873,
        "合理市盈率":28.05,
        "股息率(TTM)":3.484,
        "预测净利润(3Y)":18.8
    },
    {
        "日期":"2025-05-27",
        "股票代码":"600036",
        "股票名称":"招商银行",
        "市盈率估值":1.08,
        "净利润估值":1.24,
        "最新价":43.74,
        "市盈率估值买点":24,
        "净利润估值买点":21,
        "PE_90分位":11.65545,
        "市盈率(TTM)":7.474,
        "合理市盈率":6.945,
        "股息率(TTM)":4.508,
        "预测净利润(3Y)":1598.88
    },
    {
        "日期":"2025-05-27",
        "股票代码":"300033",
        "股票名称":"同花顺",
        "市盈率估值":1.88,
        "净利润估值":1.54,
        "最新价":250.37,
        "市盈率估值买点":66,
        "净利润估值买点":81,
        "PE_90分位":85.57238,
        "市盈率(TTM)":73.16,
        "合理市盈率":38.96,
        "股息率(TTM)":1.198,
        "预测净利润(3Y)":28.02
    },
    {
        "日期":"2025-05-27",
        "股票代码":"603605",
        "股票名称":"珀莱雅",
        "市盈率估值":0.47,
        "净利润估值":0.4,
        "最新价":89.8,
        "市盈率估值买点":95,
        "净利润估值买点":112,
        "PE_90分位":77.82616,
        "市盈率(TTM)":21.704,
        "合理市盈率":46.535,
        "股息率(TTM)":1.439,
        "预测净利润(3Y)":24.06
    },
    {
        "日期":"2025-05-27",
        "股票代码":"300896",
        "股票名称":"爱美客",
        "市盈率估值":0.42,
        "净利润估值":0.38,
        "最新价":171.07,
        "市盈率估值买点":203,
        "净利润估值买点":225,
        "PE_90分位":230.62164,
        "市盈率(TTM)":27.624,
        "合理市盈率":65.915,
        "股息率(TTM)":2.221,
        "预测净利润(3Y)":26.02
    },
    {
        "日期":"2025-05-27",
        "股票代码":"000423",
        "股票名称":"东阿阿胶",
        "市盈率估值":1.22,
        "净利润估值":0.98,
        "最新价":55.37,
        "市盈率估值买点":27,
        "净利润估值买点":33,
        "PE_90分位":67.63069,
        "市盈率(TTM)":21.895,
        "合理市盈率":17.91,
        "股息率(TTM)":5.293,
        "预测净利润(3Y)":25.44
    }
]