{
    "date": "2025-03-11",
    "positions": [
        {
            "股票代码": "600519",
            "股票名称": "贵州茅台",
            "成本价": "1900.00",
            "持仓数量": "1200",
            "当前价": 1548.68,
            "今日涨跌幅": 1.69,
            "持仓市值": 1858416.0,
            "持仓盈亏": -421584.0,
            "持仓盈亏率": -18.49
        },
        {
            "股票代码": "002304",
            "股票名称": "洋河股份",
            "成本价": "108.00",
            "持仓数量": "2000",
            "当前价": 78.28,
            "今日涨跌幅": 1.16,
            "持仓市值": 156560.0,
            "持仓盈亏": -59440.0,
            "持仓盈亏率": -27.52
        },
        {
            "股票代码": "000568",
            "股票名称": "泸州老窖",
            "成本价": "114.00",
            "持仓数量": "100",
            "当前价": 136.83,
            "今日涨跌幅": 3.56,
            "持仓市值": 13683.0,
            "持仓盈亏": 2283.0,
            "持仓盈亏率": 20.03
        },
        {
            "股票代码": "000895",
            "股票名称": "双汇发展",
            "成本价": "21.70",
            "持仓数量": "300",
            "当前价": 26.94,
            "今日涨跌幅": 0.71,
            "持仓市值": 8082.0,
            "持仓盈亏": 1572.0,
            "持仓盈亏率": 24.15
        },
        {
            "股票代码": "603259",
            "股票名称": "药明康德",
            "成本价": "56.19",
            "持仓数量": "400",
            "当前价": 61.63,
            "今日涨跌幅": -0.6,
            "持仓市值": 24652.0,
            "持仓盈亏": 2176.0,
            "持仓盈亏率": 9.68
        },
        {
            "股票代码": "hk00700",
            "股票名称": "腾讯控股",
            "成本价": "370.00",
            "持仓数量": "4900",
            "当前价": 517.5,
            "今日涨跌幅": 0.19,
            "持仓市值": 2370926.25,
            "持仓盈亏": 675771.25,
            "持仓盈亏率": 39.86
        },
        {
            "股票代码": "000000",
            "股票名称": "现金",
            "成本价": "1.00",
            "持仓数量": "13092",
            "当前价": 1.0,
            "今日涨跌幅": 0.0,
            "持仓市值": 13092.0,
            "持仓盈亏": 0.0,
            "持仓盈亏率": 0.0
        }
    ],
    "portfolio_value": 4445411.25,
    "investment_cost": 4100000.0
}